simplegooglescraper/__init__.py
simplegooglescraper/custom_exceptions.py
simplegooglescraper/logger.py
simplegooglescraper/scrapeGooGle_results.py
simple_google_scraper-0.1.1.dist-info/LICENSE
simple_google_scraper-0.1.1.dist-info/METADATA
simple_google_scraper-0.1.1.dist-info/WHEEL
simple_google_scraper-0.1.1.dist-info/top_level.txt
simple_google_scraper-0.1.1.dist-info/RECORD
